dymo_bluetooth/__init__.py
dymo_bluetooth/__main__.py
dymo_bluetooth/bluetooth.py
dymo_bluetooth/printer.py
dymo_bluetooth-0.1.2.dist-info/licenses/LICENSE
dymo_bluetooth-0.1.2.dist-info/METADATA
dymo_bluetooth-0.1.2.dist-info/WHEEL
dymo_bluetooth-0.1.2.dist-info/entry_points.txt
dymo_bluetooth-0.1.2.dist-info/top_level.txt
dymo_bluetooth-0.1.2.dist-info/RECORD
