Metadata-Version: 2.4
Name: dymo-bluetooth
Version: 0.1.2
Summary: Print labels on DYMO LT-200B over Bluetooth.
Author: ysfchn
License-Expression: MIT
Project-URL: GitHub, https://github.com/ysfchn/dymo-bluetooth
Classifier: Programming Language :: Python :: 3.10
Classifier: Programming Language :: Python :: 3.9
Classifier: Development Status :: 5 - Production/Stable
Classifier: Operating System :: OS Independent
Classifier: Topic :: System :: Hardware
Classifier: Topic :: Printing
Requires-Python: >=3.9
License-File: LICENSE
Requires-Dist: bleak~=0.22.2
Requires-Dist: pillow~=11.0.0
Provides-Extra: full
Requires-Dist: python-barcode[images]~=0.15.1; extra == "full"
Dynamic: license-file
